{
	"info": {
		"_postman_id": "130235a0-5165-45e6-afbd-e1b81a7e183b",
		"name": "Eclerx2025",
		"schema": "https://schema.getpostman.com/json/collection/v2.1.0/collection.json",
		"_exporter_id": "425296"
	},
	"item": [
		{
			"name": "RESTAPI",
			"item": [
				{
					"name": "Fetch All Employees",
					"request": {
						"method": "GET",
						"header": [],
						"url": {
							"raw": "http://localhost:9090/api/v1/employees",
							"protocol": "http",
							"host": [
								"localhost"
							],
							"port": "9090",
							"path": [
								"api",
								"v1",
								"employees"
							]
						}
					},
					"response": []
				}
			]
		}
	]
}